odoo/addons/l10n_es_aeat_mod216/README.rst
odoo/addons/l10n_es_aeat_mod216/__init__.py
odoo/addons/l10n_es_aeat_mod216/__manifest__.py
odoo/addons/l10n_es_aeat_mod216/data/l10n.es.aeat.map.tax.line.tax.csv
odoo/addons/l10n_es_aeat_mod216/data/2016/aeat_export_mod216_data.xml
odoo/addons/l10n_es_aeat_mod216/data/2016/l10n.es.aeat.map.tax.csv
odoo/addons/l10n_es_aeat_mod216/data/2016/l10n.es.aeat.map.tax.line.csv
odoo/addons/l10n_es_aeat_mod216/data/2024/aeat.model.export.config.csv
odoo/addons/l10n_es_aeat_mod216/data/2024/aeat.model.export.config.line.csv
odoo/addons/l10n_es_aeat_mod216/data/2024/l10n.es.aeat.map.tax.csv
odoo/addons/l10n_es_aeat_mod216/data/2024/l10n.es.aeat.map.tax.line.csv
odoo/addons/l10n_es_aeat_mod216/docs/DR-216e16_v1.06.pdf
odoo/addons/l10n_es_aeat_mod216/i18n/bg.po
odoo/addons/l10n_es_aeat_mod216/i18n/ca.po
odoo/addons/l10n_es_aeat_mod216/i18n/cs.po
odoo/addons/l10n_es_aeat_mod216/i18n/de.po
odoo/addons/l10n_es_aeat_mod216/i18n/es.po
odoo/addons/l10n_es_aeat_mod216/i18n/es_CO.po
odoo/addons/l10n_es_aeat_mod216/i18n/es_CR.po
odoo/addons/l10n_es_aeat_mod216/i18n/es_ES.po
odoo/addons/l10n_es_aeat_mod216/i18n/eu.po
odoo/addons/l10n_es_aeat_mod216/i18n/fr.po
odoo/addons/l10n_es_aeat_mod216/i18n/gl.po
odoo/addons/l10n_es_aeat_mod216/i18n/hr.po
odoo/addons/l10n_es_aeat_mod216/i18n/l10n_es_aeat_mod216.pot
odoo/addons/l10n_es_aeat_mod216/i18n/nl.po
odoo/addons/l10n_es_aeat_mod216/i18n/pl.po
odoo/addons/l10n_es_aeat_mod216/i18n/pt.po
odoo/addons/l10n_es_aeat_mod216/i18n/pt_BR.po
odoo/addons/l10n_es_aeat_mod216/i18n/ru.po
odoo/addons/l10n_es_aeat_mod216/i18n/sl.po
odoo/addons/l10n_es_aeat_mod216/i18n/sv.po
odoo/addons/l10n_es_aeat_mod216/i18n/tr.po
odoo/addons/l10n_es_aeat_mod216/i18n/vi.po
odoo/addons/l10n_es_aeat_mod216/models/__init__.py
odoo/addons/l10n_es_aeat_mod216/models/mod216.py
odoo/addons/l10n_es_aeat_mod216/readme/CONFIGURE.md
odoo/addons/l10n_es_aeat_mod216/readme/CONTRIBUTORS.md
odoo/addons/l10n_es_aeat_mod216/readme/DESCRIPTION.md
odoo_addon_l10n_es_aeat_mod216-18.0.1.1.2.dist-info/METADATA
odoo_addon_l10n_es_aeat_mod216-18.0.1.1.2.dist-info/WHEEL
odoo_addon_l10n_es_aeat_mod216-18.0.1.1.2.dist-info/top_level.txt
odoo_addon_l10n_es_aeat_mod216-18.0.1.1.2.dist-info/RECORD
